callback_executor/__init__.py
callback_executor/executor.py
callback_executor-0.0.1.dist-info/LICENCE
callback_executor-0.0.1.dist-info/METADATA
callback_executor-0.0.1.dist-info/WHEEL
callback_executor-0.0.1.dist-info/top_level.txt
callback_executor-0.0.1.dist-info/RECORD
