Metadata-Version: 2.1
Name: callback-executor
Version: 0.0.1
Summary: A callback queue that execute each callback in a minimum period of time.
Home-page: https://github.com/wladimirguerra/callback_executor
Author: Wladimir Guerra
Author-email: wladimir.guerra.dev@gmail.com
License: UNKNOWN
Project-URL: Bug Tracker, https://github.com/wladimirguerra/callback_executor/issues
Platform: UNKNOWN
Classifier: Programming Language :: Python :: 3
Classifier: License :: OSI Approved :: MIT License
Classifier: Operating System :: OS Independent
Requires-Python: >=3.9
License-File: LICENCE
